{
  "slug": "kitten-health-prevention",
  "en": {
    "title": "Kitten Disease Prevention Guide | What to Watch for in the First Year",
    "content": "<p>During a kitten's first year, the immune system is still developing, making disease prevention especially important.</p>\n<h2>The Three Pillars of Prevention</h2>\n<h3>1. Vaccination</h3><p>Combination vaccines administered according to the kitten's age prevent major infectious diseases.</p>\n<h3>2. Regular Deworming</h3><p>Prevent internal parasites (roundworms, tapeworms, etc.) and external parasites (fleas, ticks).</p>\n<h3>3. Daily Observation</h3><p>Check appetite, elimination, activity level, and coat condition every day. If you notice changes, address them promptly.</p>\n    <h2>Fuluck Cattery's Health Management</h2><p>Before handover, we perform vaccinations, deworming, virus testing, and health checks. If you have any health-related concerns after adoption, feel free to contact us anytime via LINE.</p>"
  },
  "zh": {
    "title": "小猫疾病预防指南 | 第一年需要注意的事项",
    "content": "<p>小猫的第一年免疫系统尚在发育中，因此疾病预防尤为重要。</p>\n<h2>预防三大支柱</h2>\n<h3>1. 疫苗接种</h3><p>根据小猫月龄接种联合疫苗，预防主要传染病。</p>\n<h3>2. 定期驱虫</h3><p>预防体内寄生虫（蛔虫、绦虫等）和体外寄生虫（跳蚤、蜱虫）。</p>\n<h3>3. 日常观察</h3><p>每天检查食欲、排泄、活动量和毛发状况。发现异常时及早处理。</p>\n    <h2>福楽猫舍的健康管理</h2><p>在交接前，我们会完成疫苗接种、驱虫、病毒检测和健康检查。领养后如有任何健康方面的疑虑，欢迎随时通过LINE联系我们。</p>"
  }
}
